maslourl/__init__.py
maslourl/models/__init__.py
maslourl/models/maslou_rl.py
maslourl/models/replay_buffer.py
maslourl/models/utils.py
maslourl/models/continuing/__init__.py
maslourl/models/continuing/ddpg.py
maslourl/models/continuing/ppo.py
maslourl/models/discrete/__init__ .py
maslourl/models/discrete/ddqn.py
maslourl/models/discrete/ppo.py
maslourl/trackers/__init__.py
maslourl/trackers/average_tracker.py
maslourl/trackers/file_logger.py
maslourl-1.5.0.dist-info/METADATA
maslourl-1.5.0.dist-info/WHEEL
maslourl-1.5.0.dist-info/licenses/LICENSE
maslourl-1.5.0.dist-info/RECORD
