Metadata-Version: 2.1
Name: maslourl
Version: 1.5.0
Summary: Framework for rl algorithms
Project-URL: Homepage, https://github.com/masalskyi/maslourl
Author-email: Ruslan Masalskyi <masalskyi@stud.onu.edu.ua>
License: MIT License
Classifier: License :: OSI Approved :: MIT License
Classifier: Operating System :: OS Independent
Classifier: Programming Language :: Python :: 3
Requires-Python: >=3.8
Requires-Dist: torch
